metamock/__init__.py
metamock/cli.py
metamock/config.py
metamock/default.config
metamock/metadata.py
metamock/otp.py
metamock/prompt.py
metamock/routes.py
metamock/server.py
metamock/util.py
metamock/version.py
metamock/views/manage.tpl
metamock-0.2.5.dist-info/entry_points.txt
metamock-0.2.5.dist-info/LICENSE
metamock-0.2.5.dist-info/WHEEL
metamock-0.2.5.dist-info/METADATA
metamock-0.2.5.dist-info/RECORD
