Metadata-Version: 2.1
Name: metamock
Version: 0.2.5
Summary: Top-level package for metamock.
Keywords: metamock
Author-email: Matt Krueger <mkrueger@rstms.net>
Classifier: Intended Audience :: Developers
Classifier: Natural Language :: English
Classifier: Programming Language :: Python :: 3
Classifier: Programming Language :: Python :: 3.10
Requires-Dist: click == 8.0.3
Requires-Dist: boto == 2.49.0
Requires-Dist: bottle == 0.12.21
Requires-Dist: black==22.3.0 ; extra == "dev"
Requires-Dist: bump2version==1.0.1 ; extra == "dev"
Requires-Dist: coverage==6.2 ; extra == "dev"
Requires-Dist: flake8==4.0.1 ; extra == "dev"
Requires-Dist: flit==3.7.1 ; extra == "dev"
Requires-Dist: isort==5.10.1 ; extra == "dev"
Requires-Dist: pytest==6.2.5 ; extra == "dev"
Requires-Dist: pytest-datadir==1.3.1 ; extra == "dev"
Requires-Dist: tox==3.24.4 ; extra == "dev"
Requires-Dist: sphinx==4.3.2 ; extra == "docs"
Requires-Dist: sphinx-click==3.0.2 ; extra == "docs"
Requires-Dist: sphinx-rtd-theme==1.0.0 ; extra == "docs"
Project-URL: Home, https://github.com/rstms/metamock
Provides-Extra: dev
Provides-Extra: docs
